{"db":[{"classes":[{"String":{}},{"Number":{}},{"Boolean":{}},{"Point":{"x":"Number","y":"Number"}},{"Size":{"width":"Number","height":"Number"}},{"Vector":{"dx":"Number","dy":"Number"}},{"Rectangle":{"size":"Size","location":"Point"}},{"Position":{"location":"Point","direction":"Vector"}},{"Node":{"next":"Node","isFirst":"Boolean","location":"Point","direction":"Vector"}},{"Stone":{"strong":"Number","location":"Point"}},{"Mine":{"name":"String","kor":"Number","stone":"Stone"}},{"Entity":{"x":"Number","width":"Number","y":"Number","height":"Number"}}]},{"azeroth":[{"0":{"zindex":0,"zlayer":0,"className":"String","value":"körteee"}},{"1":{"zindex":0,"zlayer":0,"className":"Number","value":50}},{"2":{"zindex":0,"zlayer":0,"className":"Number","value":321}},{"3":{"zindex":0,"zlayer":0,"className":"Boolean","value":true}},{"4":{"zindex":0,"zlayer":2,"@x":1,"@y":2,"className":"Point"}},{"5":{"zindex":1,"zlayer":2,"className":"Rectangle","@size":4,"@location":4}},{"6":{"zindex":2,"@strong":1,"zlayer":2,"className":"Stone","@location":4}},{"7":{"@kor":1,"zindex":0,"@name":0,"@stone":6,"zlayer":0,"className":"Mine"}},{"8":{"zindex":0,"zlayer":0,"className":"String","value":"ValamiName"}},{"9":{"zindex":0,"zlayer":0,"className":"Number","value":1111}},{"10":{"zindex":0,"zlayer":0,"className":"Number","value":11}},{"11":{"zindex":0,"zlayer":0,"className":"Number","value":123}},{"12":{"zindex":0,"zlayer":0,"className":"Number","value":321}},{"13":{"zindex":0,"zlayer":88,"@x":11,"@y":12,"className":"Point"}},{"14":{"zindex":1,"@strong":10,"zlayer":88,"className":"Stone","@location":13}},{"15":{"@kor":9,"zindex":2,"@name":8,"@stone":14,"zlayer":88,"className":"Mine"}},{"16":{"zindex":0,"zlayer":0,"className":"Number","value":10}},{"17":{"zindex":0,"zlayer":0,"className":"Number","value":20}},{"18":{"zindex":0,"zlayer":0,"className":"Number","value":30}},{"19":{"zindex":0,"zlayer":0,"className":"Number","value":40}},{"20":{"@height":19,"zindex":0,"@width":18,"zlayer":88,"@x":16,"@y":17,"className":"Entity"}},{"21":{"zindex":0,"zlayer":0,"className":"Number","value":100}},{"22":{"zindex":0,"zlayer":0,"className":"Number","value":200}},{"23":{"zindex":0,"zlayer":0,"className":"Number","value":30}},{"24":{"zindex":0,"zlayer":0,"className":"Number","value":40}},{"25":{"@height":24,"zindex":0,"@width":23,"zlayer":88,"@x":21,"@y":22,"className":"Entity"}},{"26":{"zindex":0,"zlayer":0,"className":"Number","value":150}},{"27":{"zindex":0,"zlayer":0,"className":"Number","value":200}},{"28":{"zindex":0,"zlayer":0,"className":"Number","value":30}},{"29":{"zindex":0,"zlayer":0,"className":"Number","value":40}},{"30":{"@height":29,"zindex":0,"@width":28,"zlayer":88,"@x":26,"@y":27,"className":"Entity"}},{"31":{"zindex":0,"zlayer":0,"className":"Number","value":150}},{"32":{"zindex":0,"zlayer":0,"className":"Number","value":2000}},{"33":{"zindex":0,"zlayer":0,"className":"Number","value":30}},{"34":{"zindex":0,"zlayer":0,"className":"Number","value":40}},{"35":{"@height":34,"zindex":0,"@width":33,"zlayer":88,"@x":31,"@y":32,"className":"Entity"}},{"36":{"zindex":0,"zlayer":0,"className":"Number","value":1000}},{"37":{"zindex":0,"zlayer":0,"className":"Number","value":1000}},{"38":{"zindex":0,"zlayer":0,"className":"Number","value":30}},{"39":{"zindex":0,"zlayer":0,"className":"Number","value":40}},{"40":{"@height":39,"zindex":0,"@width":38,"zlayer":88,"@x":36,"@y":37,"className":"Entity"}},{"41":{"zindex":0,"zlayer":0,"className":"Number","value":500}},{"42":{"zindex":0,"zlayer":0,"className":"Number","value":500}},{"43":{"zindex":0,"zlayer":0,"className":"Number","value":30}},{"44":{"zindex":0,"zlayer":0,"className":"Number","value":40}},{"45":{"@height":44,"zindex":0,"@width":43,"zlayer":88,"@x":41,"@y":42,"className":"Entity"}},{"46":{"zindex":0,"zlayer":0,"className":"Number","value":600}},{"47":{"zindex":0,"zlayer":0,"className":"Number","value":500}},{"48":{"zindex":0,"zlayer":0,"className":"Number","value":30}},{"49":{"zindex":0,"zlayer":0,"className":"Number","value":40}},{"50":{"@height":49,"zindex":0,"@width":48,"zlayer":88,"@x":46,"@y":47,"className":"Entity"}}]},{"og":[{"0":{"zindex":0,"zlayer":0,"className":"String","value":"körteee"}},{"1":{"zindex":0,"zlayer":0,"className":"Number","value":12}},{"2":{"zindex":0,"zlayer":0,"className":"Number","value":321}},{"3":{"zindex":0,"zlayer":0,"className":"Boolean","value":true}},{"4":{"zindex":0,"zlayer":2,"@x":1,"@y":2,"className":"Point"}},{"5":{"zindex":1,"zlayer":2,"className":"Rectangle","@size":4,"@location":4}},{"6":{"zindex":2,"@strong":1,"zlayer":2,"className":"Stone","@location":4}}]}]}